{
  "contact": {
    "email": "example@email.com",
    "name": "Jane Doe",
    "phone": "+1-123-456-7890",
    "links": [
      {
        "link": "linkedin.com/in/janedoe"
      },
      {
        "link": "github.com/janedoe"
      }
    ]
  },
  "education": [
    {
      "degree": "Bachelor of Science in Software Engineering",
      "school": "University of Fictional",
      "suffixes": [
        "Magna Cum Laude",
        "Research Distinction"
      ],
      "details": [
        {
          "category": "Certificate",
          "value": "Specialization in Data Science"
        },
        {
          "category": "Notable Achievements",
          "value": "Dean's List (2018, 2019), Undergraduate Research Award"
        }
      ],
      "dates": {
        "start": "2017-09-01",
        "end": "2021-06-30"
      },
      "location": {
        "city": "Imaginary City",
        "state": "Stateville"
      }
    }
  ],
  "experience": [
    {
      "company": "Tech Innovations Inc.",
      "title": "Software Developer",
      "achievements": [
        "Developed a cloud-based storage solution improving data retrieval efficiency by 40%",
        "Collaborated on a team project to create a cross-platform mobile application"
      ],
      "dates": {
        "start": "2021-07-01"
      },
      "location": {
        "city": "Imaginary City",
        "state": "Stateville"
      }
    },
    {
      "company": "NextGen Solutions",
      "title": "Junior Developer",
      "achievements": [
        "Assisted in developing APIs for internal tools, improving workflow by 25%",
        "Participated in a hackathon and won second place for a machine learning project"
      ],
      "dates": {
        "start": "2020-01-01",
        "end": "2021-06-30"
      },
      "location": {
        "city": "Dreamtown",
        "state": "Futureland"
      }
    }
  ],
  "skills": [
    {
      "category": "Programming Languages",
      "value": "Python, Java, C++, JavaScript"
    },
    {
      "category": "Tools & Frameworks",
      "value": "AWS, Docker, React, Node.js"
    }
  ],
  "projects": [
    {
      "name": "Personal Finance Tracker",
      "language": "Python, JavaScript",
      "details": "Developed a web application for personal finance management",
      "link": "https://github.com/janedoe/finance-tracker"
    }
  ]
}